mossspider/__init__.py
mossspider/dgm.py
mossspider/version.py
mossspider/estimators/__init__.py
mossspider/estimators/tmle.py
mossspider/estimators/utils.py
mossspider-0.0.3.dist-info/LICENSE
mossspider-0.0.3.dist-info/METADATA
mossspider-0.0.3.dist-info/WHEEL
mossspider-0.0.3.dist-info/top_level.txt
mossspider-0.0.3.dist-info/RECORD
