Metadata-Version: 2.1
Name: mossspider
Version: 0.0.3
Summary: Targeted maximum likelihood estimation for network-dependent data
Home-page: https://github.com/pzivich/MossSpider/
Author: Paul Zivich
Author-email: zivich.5@gmail.com
License: MIT
Keywords: tmle network
Platform: UNKNOWN
Classifier: Programming Language :: Python :: 3.6
Classifier: Programming Language :: Python :: 3.7
Classifier: Programming Language :: Python :: 3.8
Classifier: Programming Language :: Python :: 3.9
Classifier: Programming Language :: Python :: 3.10
Requires-Dist: numpy
Requires-Dist: scipy
Requires-Dist: pandas
Requires-Dist: networkx (>=2.0.0)
Requires-Dist: matplotlib
Requires-Dist: statsmodels
Requires-Dist: patsy
